nonebot/adapters/onebot/__init__.py
nonebot/adapters/onebot/collator.py
nonebot/adapters/onebot/compat.py
nonebot/adapters/onebot/store.py
nonebot/adapters/onebot/utils.py
nonebot/adapters/onebot/v11/__init__.py
nonebot/adapters/onebot/v11/adapter.py
nonebot/adapters/onebot/v11/bot.py
nonebot/adapters/onebot/v11/bot.pyi
nonebot/adapters/onebot/v11/config.py
nonebot/adapters/onebot/v11/event.py
nonebot/adapters/onebot/v11/exception.py
nonebot/adapters/onebot/v11/helpers.py
nonebot/adapters/onebot/v11/message.py
nonebot/adapters/onebot/v11/permission.py
nonebot/adapters/onebot/v11/utils.py
nonebot/adapters/onebot/v12/__init__.py
nonebot/adapters/onebot/v12/adapter.py
nonebot/adapters/onebot/v12/bot.py
nonebot/adapters/onebot/v12/bot.pyi
nonebot/adapters/onebot/v12/config.py
nonebot/adapters/onebot/v12/event.py
nonebot/adapters/onebot/v12/exception.py
nonebot/adapters/onebot/v12/message.py
nonebot/adapters/onebot/v12/permission.py
nonebot/adapters/onebot/v12/utils.py
nonebot_adapter_onebot_migang_memes-0.0.1.dist-info/LICENSE
nonebot_adapter_onebot_migang_memes-0.0.1.dist-info/METADATA
nonebot_adapter_onebot_migang_memes-0.0.1.dist-info/WHEEL
nonebot_adapter_onebot_migang_memes-0.0.1.dist-info/RECORD
